pydra/tasks/ants/__init__.py
pydra/tasks/ants/_version.py
pydra/tasks/ants/latest.py
pydra/tasks/ants/v2/__init__.py
pydra/tasks/ants/v2/_post_release.py
pydra/tasks/ants/v2/base.py
pydra/tasks/ants/v2/legacy/__init__.py
pydra/tasks/ants/v2/legacy/ants_introduction.py
pydra/tasks/ants/v2/legacy/buildtemplateparallel.py
pydra/tasks/ants/v2/legacy/gen_warp_fields.py
pydra/tasks/ants/v2/nipype_ports/__init__.py
pydra/tasks/ants/v2/nipype_ports/utils/__init__.py
pydra/tasks/ants/v2/nipype_ports/utils/filemanip.py
pydra/tasks/ants/v2/nipype_ports/utils/misc.py
pydra/tasks/ants/v2/registration/__init__.py
pydra/tasks/ants/v2/registration/ants.py
pydra/tasks/ants/v2/registration/composite_transform_util.py
pydra/tasks/ants/v2/registration/measure_image_similarity.py
pydra/tasks/ants/v2/registration/registration.py
pydra/tasks/ants/v2/registration/registration_syn_quick.py
pydra/tasks/ants/v2/resampling/__init__.py
pydra/tasks/ants/v2/resampling/apply_transforms.py
pydra/tasks/ants/v2/resampling/apply_transforms_to_points.py
pydra/tasks/ants/v2/resampling/warp_image_multi_transform.py
pydra/tasks/ants/v2/resampling/warp_time_series_image_multi_transform.py
pydra/tasks/ants/v2/segmentation/__init__.py
pydra/tasks/ants/v2/segmentation/atropos.py
pydra/tasks/ants/v2/segmentation/brain_extraction.py
pydra/tasks/ants/v2/segmentation/cortical_thickness.py
pydra/tasks/ants/v2/segmentation/denoise_image.py
pydra/tasks/ants/v2/segmentation/joint_fusion.py
pydra/tasks/ants/v2/segmentation/kelly_kapowski.py
pydra/tasks/ants/v2/segmentation/laplacian_thickness.py
pydra/tasks/ants/v2/segmentation/n4_bias_field_correction.py
pydra/tasks/ants/v2/utils/__init__.py
pydra/tasks/ants/v2/utils/affine_initializer.py
pydra/tasks/ants/v2/utils/ai.py
pydra/tasks/ants/v2/utils/average_affine_transform.py
pydra/tasks/ants/v2/utils/average_images.py
pydra/tasks/ants/v2/utils/compose_multi_transform.py
pydra/tasks/ants/v2/utils/create_jacobian_determinant_image.py
pydra_tasks_ants-0.2.2.dist-info/METADATA
pydra_tasks_ants-0.2.2.dist-info/WHEEL
pydra_tasks_ants-0.2.2.dist-info/licenses/LICENSE
pydra_tasks_ants-0.2.2.dist-info/licenses/NOTICE
pydra_tasks_ants-0.2.2.dist-info/RECORD
