Metadata-Version: 2.4
Name: pydra-tasks-ants
Version: 0.2.2
Summary: Pydra tasks package for ANTs
Project-URL: Documentation, https://github.com/nipype/pydra-tasks-ants#readme
Project-URL: Issues, https://github.com/nipype/pydra-tasks-ants/issues
Project-URL: Source, https://github.com/nipype/pydra-tasks-ants
Author-email: Ghislain Vaillant <ghislain.vaillant@icm-institute.org>, Nipype developers <neuroimaging@python.org>
Maintainer-email: Nipype developers <neuroimaging@python.org>
License:                                  Apache License
License-File: LICENSE
License-File: NOTICE
Keywords: ants,neuroimaging,pydra,registration
Classifier: Development Status :: 3 - Alpha
Classifier: Intended Audience :: Science/Research
Classifier: License :: OSI Approved :: Apache Software License
Classifier: Operating System :: OS Independent
Classifier: Programming Language :: Python :: 3
Classifier: Programming Language :: Python :: 3.11
Classifier: Programming Language :: Python :: 3.12
Classifier: Programming Language :: Python :: 3.13
Classifier: Topic :: Scientific/Engineering
Classifier: Topic :: Software Development :: Libraries
Requires-Python: >=3.11
Requires-Dist: fileformats-datascience>=0.3.2
Requires-Dist: fileformats-medimage>=0.10.5
Requires-Dist: fileformats>=0.15.4
Requires-Dist: pydra>=1.0a2
Provides-Extra: dev
Requires-Dist: black; extra == 'dev'
Requires-Dist: pre-commit; extra == 'dev'
Provides-Extra: test
Requires-Dist: codecov; extra == 'test'
Requires-Dist: fileformats-datascience-extras; extra == 'test'
Requires-Dist: fileformats-extras; extra == 'test'
Requires-Dist: nipype2pydra>=0.5.0; extra == 'test'
Requires-Dist: pluggy>=1.2; extra == 'test'
Requires-Dist: pytest-cov>=4.1.0; extra == 'test'
Requires-Dist: pytest-env; extra == 'test'
Requires-Dist: pytest-rerunfailures; extra == 'test'
Requires-Dist: pytest-xdist>=3.5.0; extra == 'test'
Requires-Dist: pytest>=7.4; extra == 'test'
